[
  {
    "type": "scenario",
    "id": "fvi_bionic_scenario",
    "name": "Unkind Android",
    "points": 15,
    "description": "You were meant to be humanity's last bastion. The ultimate weapon, held in reserve for a final effort to reclaim the world. That day never came. Instead, you awoke to silence, remotely activated by a deadman switch after two weeks without an all-clear signal. Whatever happened outside, there was nobody left to give the order.",
	"flags": [ "CITY_START", "LONE_START" ],
    "allowed_locs": [ "sloc_basement_bionic" ],
    "professions": [ "fox_android" ],
    "start_name": "Rude Awakening"
  },
  {
    "type": "profession",
    "id": "fox_android",
    "name": "Biosynthetic Android: Vulpine Module",
    "description": "A bionsynthetic living weapon, you were designed to be the shift in balance during humanity's last stand. Instead, a failsafe activated you after two weeks of no all clear signal.",
    "points": 15,
	"traits": [ "PROF_MILITARY" ],
    "skills": [
      { "level": 1, "name": "swimming" },
      { "level": 1, "name": "firstaid" },
      { "level": 2, "name": "gun" },
      { "level": 2, "name": "melee" },
      { "level": 2, "name": "rifle" },
      { "level": 1, "name": "stabbing" },
      { "level": 1, "name": "dodge" },
	  { "level": 2, "name": "survival" },
	  { "level": 1, "name": "fabrication" },
      { "level": 1, "name": "throw" }
    ],
    "CBMs": [
      "bio_android_toolset",
      "bio_quantum_reactor",
      "bio_fox_ears_cbm",
      "bio_fox_tail_cbm",
      "bio_ups",
      "bio_targeting",
      "bio_geiger",
      "bio_power_armor_interface",
      "bio_cqb",
      "bio_blade",
      "bio_weight",
	  "bio_quantum_battery",
	  "bio_carbon",
	  "bio_eye_enhancer",
      "bio_climate",
      "bio_evap",
	  "bio_tools",
	  "bio_leukocyte",
	  "bio_purifier"
    ],
    "items": {
      "both": {
        "items": [		  
		  "winter_pants_army",
          "tshirt",
          "winter_jacket_army",
          "winter_gloves_army",
          "socks",
          "boots_combat",
          "wristwatch",
          "canteen",
          "AndroidQuantumStorageMatrix" ]
      }
    },
    "flags": [ "SCEN_ONLY" ]
  }
]
